tidysdmx/__init__.py
tidysdmx/kedro.py
tidysdmx/mapping.py
tidysdmx/qa_utils.py
tidysdmx/structures.py
tidysdmx/tidy_raw.py
tidysdmx/tidysdmx.py
tidysdmx/utils.py
tidysdmx/validation.py
tidysdmx-0.7.5.dist-info/LICENSE
tidysdmx-0.7.5.dist-info/METADATA
tidysdmx-0.7.5.dist-info/WHEEL
tidysdmx-0.7.5.dist-info/RECORD
