Metadata-Version: 2.3
Name: tidysdmx
Version: 0.7.5
Summary: A toolbox to work with SDMX data
License: MIT
Author: Tony Fujs
Requires-Python: >=3.11.9
Classifier: License :: OSI Approved :: MIT License
Classifier: Programming Language :: Python :: 3
Classifier: Programming Language :: Python :: 3.12
Classifier: Programming Language :: Python :: 3.13
Requires-Dist: openpyxl (>=3.1.5,<4.0.0)
Requires-Dist: pandas (>=2.2.3,<3.0.0)
Requires-Dist: pysdmx (>=1.8.1)
Requires-Dist: typeguard (>=4.4.4,<5.0.0)
